vecposlib/__init__.py
vecposlib/common.py
vecposlib/py.typed
vecposlib/positionlib/__init__.py
vecposlib/positionlib/position.py
vecposlib/positionlib/position.pyi
vecposlib/vectorlib/__init__.py
vecposlib/vectorlib/vector.py
vecposlib/vectorlib/vector.pyi
vecposlib-1.0.4.dist-info/licenses/LICENSE.md
vecposlib-1.0.4.dist-info/METADATA
vecposlib-1.0.4.dist-info/WHEEL
vecposlib-1.0.4.dist-info/top_level.txt
vecposlib-1.0.4.dist-info/RECORD
