Metadata-Version: 2.4
Name: VecPosLib
Version: 1.0.4
Summary: Library for vector calculations in Python
Home-page: https://github.com/shotadft/VecPosLib
Author: Shotadft
Author-email: Shotadft <98450322+shotadft@users.noreply.github.com>
License: MIT License
Project-URL: Repository, https://github.com/shotadft/VecPosLib
Project-URL: Homepage, https://github.com/shotadft/VecPosLib
Project-URL: Issues, https://github.com/shotadft/VecPosLib/issues
Keywords: vector,math,numpy,cupy,numba,linear algebra,gpu,coordinates,scientific computing
Classifier: Programming Language :: Python :: 3.13
Classifier: Operating System :: OS Independent
Classifier: Typing :: Typed
Classifier: License :: OSI Approved :: MIT License
Requires-Python: >=3.13
License-File: LICENSE.md
Requires-Dist: numpy<2.3,>=2.2.0
Requires-Dist: numba>=0.61.2
Provides-Extra: cupy
Requires-Dist: cupy; extra == "cupy"
Dynamic: author
Dynamic: home-page
Dynamic: license-file
Dynamic: requires-python
